setup.py
bouncer/__init__.py
bouncer/admin.py
bouncer/functions.py
bouncer/middleware.py
bouncer/models.py
bouncer/signals.py
django_bouncer.egg-info/PKG-INFO
django_bouncer.egg-info/SOURCES.txt
django_bouncer.egg-info/dependency_links.txt
django_bouncer.egg-info/top_level.txt