Metadata-Version: 1.0
Name: django-bouncer
Version: 0.2
Summary: Allows you (or users of your site) to invite new people to join
Home-page: http://github.com/shelfworthy/django-bouncer
Author: Chris Drackett
Author-email: chris@shelfworthy.com
License: UNKNOWN
Platform: UNKNOWN
Classifier: Development Status :: 2 - Pre-Alpha
Classifier: Environment :: Web Environment
Classifier: Intended Audience :: Developers
Classifier: Natural Language :: English
Classifier: License :: OSI Approved :: BSD License
Classifier: Operating System :: OS Independent
Classifier: Programming Language :: Python
Classifier: Framework :: Django
Classifier: Topic :: Utilities
